{
  "project_info": {
    "project_number": "798921772901",
    "project_id": "fc-events-app-f305c",
    "storage_bucket": "fc-events-app-f305c.appspot.com"
  },
  "client": [
    {
      "client_info": {
        "mobilesdk_app_id": "1:798921772901:android:7e20dfc986f30635561b8c",
        "android_client_info": {
          "package_name": "com.example.hello"
        }
      },
      "oauth_client": [
        {
          "client_id": "798921772901-ki0gceujn6uto9ip41vek02o7fvb36lb.apps.googleusercontent.com",
          "client_type": 3
        }
      ],
      "api_key": [
        {
          "current_key": "AIzaSyDLl0w0jNhp7v6O8yCnZaBtISnpLig22xM"
        }
      ],
      "services": {
        "appinvite_service": {
          "other_platform_oauth_client": [
            {
              "client_id": "798921772901-ki0gceujn6uto9ip41vek02o7fvb36lb.apps.googleusercontent.com",
              "client_type": 3
            }
          ]
        }
      }
    }
  ],
  "configuration_version": "1"
}